notashark/__init__.py
notashark/__main__.py
notashark/cli.py
notashark/discord_bot.py
notashark/embeds.py
notashark/fetcher.py
notashark/parts.py
notashark/settings.py
notashark-1.1.1.dist-info/LICENSE
notashark-1.1.1.dist-info/METADATA
notashark-1.1.1.dist-info/WHEEL
notashark-1.1.1.dist-info/entry_points.txt
notashark-1.1.1.dist-info/top_level.txt
notashark-1.1.1.dist-info/RECORD
