Metadata-Version: 2.1
Name: notashark
Version: 1.1.1
Summary: notashark - a discord bot for King Arthur's Gold
Home-page: https://github.com/moonburnt/notashark
Author: moonburnt
Author-email: moonburnt <moonburnt@disroot.org>
License: GNU GENERAL PUBLIC LICENSE
Project-URL: homepage, https://github.com/moonburnt/notashark
Classifier: Programming Language :: Python :: 3
Classifier: Development Status :: 5 - Production/Stable
Classifier: License :: OSI Approved :: GNU General Public License v3 (GPLv3)
Requires-Python: >=3.8
License-File: LICENSE
Requires-Dist: discord.py (==2.1.0)
Requires-Dist: requests (==2.28.1)
Requires-Dist: pykagapi (==0.2.1)
Provides-Extra: dev
Requires-Dist: black (==22.10.0) ; extra == 'dev'
